README.rst
setup.py
json_regex_diff/__init__.py
json_regex_diff/jsondiff.py
json_regex_difftool.egg-info/PKG-INFO
json_regex_difftool.egg-info/SOURCES.txt
json_regex_difftool.egg-info/dependency_links.txt
json_regex_difftool.egg-info/entry_points.txt
json_regex_difftool.egg-info/top_level.txt