Metadata-Version: 1.1
Name: json-regex-difftool
Version: 0.2
Summary: A tool for doing a comparison or difference of JSON documentswith regular expression support
Home-page: https://github.com/bazaarvoice/json-regex-difftool.git
Author: Clayton Stout
Author-email: clayfstout@gmail.com
License: Apache Software License
Keywords: JSON,regular expressions,regex,diff,difftool
Platform: UNKNOWN
Classifier: Development Status :: 4 - Beta
Classifier: Intended Audience :: Developers
Classifier: Topic :: Utilities
Classifier: Topic :: Software Development
Classifier: Topic :: Internet :: Log Analysis
Classifier: License :: OSI Approved :: Apache Software License
Classifier: Programming Language :: Python :: 2.7
